setup.cfg
setup.py
ezcluster/__init__.py
ezcluster/base_model.py
ezcluster/kmeans.py
ezcluster/preprocessor.py
ezcluster.egg-info/PKG-INFO
ezcluster.egg-info/SOURCES.txt
ezcluster.egg-info/dependency_links.txt
ezcluster.egg-info/not-zip-safe
ezcluster.egg-info/top_level.txt