Metadata-Version: 1.1
Name: ezcluster
Version: 0.0.3
Summary: Evaluating the optimal number of clusters for KMeans clustering using the gap statistic
Home-page: https://github.com/thisisandreeeee/ezcluster
Author: Andre Tan
Author-email: tanandre93@gmail.com
License: MIT
Download-URL: https://github.com/thisisandreeeee/ezcluster/tarball/0.0.3
Keywords: kmeans,clustering,gap statistic,unsupervised learning,machine learning
Platform: UNKNOWN
Classifier: Development Status :: 5 - Production/Stable
Classifier: Intended Audience :: Developers
Classifier: License :: OSI Approved :: MIT License
Classifier: Natural Language :: English
Classifier: Programming Language :: Python :: 2
Classifier: Programming Language :: Python :: 2.7
Classifier: Programming Language :: Python :: 3
Classifier: Programming Language :: Python :: 3.1
Classifier: Programming Language :: Python :: 3.2
Classifier: Programming Language :: Python :: 3.3
Classifier: Programming Language :: Python :: 3.4
Classifier: Programming Language :: Python :: 3.5
